fitdataset/__init__.py
fitdataset/constantes_parser_dataset.py
fitdataset/dataset.py
fitdataset/dataset_nutritional.py
fitdataset/interfaces.py
fitdataset/parser.py
fitobjectivedataset-1.2.0.dist-info/METADATA
fitobjectivedataset-1.2.0.dist-info/WHEEL
fitobjectivedataset-1.2.0.dist-info/top_level.txt
fitobjectivedataset-1.2.0.dist-info/RECORD
